[
  {
    "element": "object",
    "meta": {
      "id": "Example"
    },
    "content": [
      {
        "element": "member",
        "content": {
          "key": {
            "element": "string",
            "content": "tags"
          },
          "value": {
            "element": "array",
            "content": [
              {
                "element": "string",
                "content": "hello"
              },
              {
                "element": "string",
                "content": "world"
              }
            ]
          }
        }
      }
    ]
  }
]
